lmfa/__init__.py
lmfa/__main__.py
lmfa/multifamily.py
lmfa/multifamily_analysis.py
lmfa/utilities.py
leveraged_multi_family_analysis-0.1.5.dist-info/LICENSE
leveraged_multi_family_analysis-0.1.5.dist-info/METADATA
leveraged_multi_family_analysis-0.1.5.dist-info/WHEEL
leveraged_multi_family_analysis-0.1.5.dist-info/entry_points.txt
leveraged_multi_family_analysis-0.1.5.dist-info/top_level.txt
leveraged_multi_family_analysis-0.1.5.dist-info/RECORD
