Metadata-Version: 2.1
Name: leveraged-multi-family-analysis
Version: 0.1.5
Summary: leveraged multi family housing analysis
Author-email: Vamsee Achanta <vamsee.achanta@aceengineer.com>
License: MIT License        
Project-URL: repository, https://github.com/vamseeachanta/leveraged-multi-family-analysis
Project-URL: documentation, https://github.com/vamseeachanta/leveraged-multi-family-analysis/blob/main/README.md
Keywords: realestate,multifamily,leverage,investments
Classifier: License :: OSI Approved :: MIT License
Classifier: Programming Language :: Python
Classifier: Programming Language :: Python :: 3
Requires-Python: >=3.7
License-File: LICENSE
Requires-Dist: numpy-financial
Requires-Dist: pyyaml
Requires-Dist: pandas
Requires-Dist: numpy
Requires-Dist: plotly
Requires-Dist: tomli ; python_version < "3.11"
Provides-Extra: build
Requires-Dist: build ; extra == 'build'
Requires-Dist: twine ; extra == 'build'
Provides-Extra: dev
Requires-Dist: black ; extra == 'dev'
Requires-Dist: bumpver ; extra == 'dev'
Requires-Dist: isort ; extra == 'dev'
Requires-Dist: mypy ; extra == 'dev'
Requires-Dist: pytest ; extra == 'dev'
